nlterm/__init__.py
nlterm/lib.py
nlterm-0.0.4.dist-info/METADATA
nlterm-0.0.4.dist-info/WHEEL
nlterm-0.0.4.dist-info/entry_points.txt
nlterm-0.0.4.dist-info/top_level.txt
nlterm-0.0.4.dist-info/RECORD
