Metadata-Version: 2.1
Name: nlterm
Version: 0.0.4
Summary: Terminal with ChatGPT integration
Author-email: Tom Shen <me@tomshen.io>
Project-URL: homepage, https://github.com/tsunrise/nlterm
Classifier: Programming Language :: Python :: 3
Requires-Python: >=3.7
Requires-Dist: openai
